tests/__init__.py
tests/common.py
tests/test_utils.py
tests/tests_base_trainer.py
tests/tests_callbacks.py
tests/tests_data.py
tests/tests_hparams.py
tests/tests_metrics.py
tests/tests_trainers.py
torchero/__init__.py
torchero/_version.py
torchero/base.py
torchero/hparams.py
torchero/supervised_trainer.py
torchero/unsupervised_trainers.py
torchero/callbacks/__init__.py
torchero/callbacks/base.py
torchero/callbacks/checkpoint.py
torchero/callbacks/container.py
torchero/callbacks/exceptions.py
torchero/callbacks/history.py
torchero/callbacks/logger.py
torchero/callbacks/progress_bars.py
torchero/callbacks/remote.py
torchero/callbacks/schedulers.py
torchero/callbacks/stats_exporters.py
torchero/callbacks/stopping.py
torchero/callbacks/tensorboard.py
torchero/meters/__init__.py
torchero/meters/averager.py
torchero/meters/balanced_accuracy.py
torchero/meters/base.py
torchero/meters/batch.py
torchero/meters/binary_scores.py
torchero/meters/categorical_accuracy.py
torchero/meters/confusion_matrix.py
torchero/meters/exceptions.py
torchero/meters/loss.py
torchero/meters/mse.py
torchero/meters/nullmeter.py
torchero/meters/performance.py
torchero/meters/aggregators/__init__.py
torchero/meters/aggregators/base.py
torchero/meters/aggregators/batch.py
torchero/meters/aggregators/scale.py
torchero/models/__init__.py
torchero/models/model.py
torchero/models/text/__init__.py
torchero/models/text/model.py
torchero/models/text/nn/__init__.py
torchero/models/text/nn/linear.py
torchero/models/text/nn/lstm.py
torchero/models/text/nn/transformer.py
torchero/models/vision/__init__.py
torchero/models/vision/model.py
torchero/models/vision/nn/__init__.py
torchero/models/vision/nn/torchvision.py
torchero/utils/__init__.py
torchero/utils/collate.py
torchero/utils/collections.py
torchero/utils/defaults.py
torchero/utils/format.py
torchero/utils/io.py
torchero/utils/mixins.py
torchero/utils/optimizer.py
torchero/utils/plots.py
torchero/utils/tensorboard.py
torchero/utils/data/__init__.py
torchero-0.1.0.dist-info/AUTHORS
torchero-0.1.0.dist-info/LICENSE
torchero-0.1.0.dist-info/METADATA
torchero-0.1.0.dist-info/WHEEL
torchero-0.1.0.dist-info/top_level.txt
torchero-0.1.0.dist-info/RECORD
