Metadata-Version: 2.1
Name: torchero
Version: 0.1.0
Summary: A pluggable & extensible trainer for pytorch
Home-page: http://github.com/juancruzsosa/torchero
Author: Juan Cruz Sosa
Author-email: juancruzsosa.92@gmail.com
License: MIT
Project-URL: Documentation, https://torchero.readthedocs.io
Platform: UNKNOWN
Classifier: Programming Language :: Python :: 3
Classifier: License :: OSI Approved :: MIT License
Classifier: Operating System :: OS Independent
Requires-Dist: torch
Requires-Dist: torchvision
Requires-Dist: pyyaml
Requires-Dist: tqdm
Requires-Dist: requests
Requires-Dist: matplotlib
Requires-Dist: Pillow
Requires-Dist: pandas
Provides-Extra: remotemonitor
Requires-Dist: requests ; extra == 'remotemonitor'
Provides-Extra: extra_tokenizers
Requires-Dist: spacy ; extra == 'extra_tokenizers'
Requires-Dist: nltk ; extra == 'extra_tokenizers'
